{
    "moduleId": "module_08",
    "moduleTitle": "L1 Deep Dive Module 8",
    "passingScore": 80,
    "questions": [
        {
            "id": "q8_1",
            "question": "According to Bronfenbrenner’s Socio-Ecological Model discussed in Lesson 1, which level includes the child's immediate environment, such as the family table and school lunchroom?",
            "options": [
                "The Microsystem",
                "The Mesosystem",
                "The Exosystem",
                "The Macrosystem"
            ],
            "correctAnswer": 0,
            "explanation": "The Microsystem is the most immediate environment where the child lives and interacts, including family, school, and peers."
        },
        {
            "id": "q8_2",
            "question": "In the Ellyn Satter Division of Responsibility (sDOR) framework, which of the following is the SOLE responsibility of the child?",
            "options": [
                "Deciding where the meal is eaten",
                "Deciding what food is served",
                "Deciding how much to eat (if any)",
                "Deciding when the meal is scheduled"
            ],
            "correctAnswer": 2,
            "explanation": "Under sDOR, the parent is responsible for the 'What, When, and Where,' while the child is responsible for 'How much' and 'Whether' to eat."
        },
        {
            "id": "q8_3",
            "question": "When performing an advanced growth assessment, a Z-score of -2.0 for Height-for-Age (HFA) typically indicates which clinical condition?",
            "options": [
                "Acute Malnutrition (Wasting)",
                "Chronic Malnutrition (Stunting)",
                "Normal physiological variation",
                "Pediatric Obesity"
            ],
            "correctAnswer": 1,
            "explanation": "A Z-score of -2.0 corresponds to the 2.3rd percentile; in Height-for-Age, this is the standard clinical threshold for stunting, indicating chronic nutritional deficiency."
        },
        {
            "id": "q8_4",
            "question": "Clinical protocols for remediating Iron Deficiency Anemia (IDA) in children often suggest a therapeutic dose of elemental iron in what range?",
            "options": [
                "0.5 - 1 mg/kg/day",
                "3 - 6 mg/kg/day",
                "10 - 15 mg/kg/day",
                "20 - 25 mg/kg/day"
            ],
            "correctAnswer": 1,
            "explanation": "Standard clinical protocols for therapeutic remediation of IDA typically range from 3 to 6 mg of elemental iron per kilogram of body weight per day, divided into 1-3 doses."
        },
        {
            "id": "q8_5",
            "question": "Which neurotransmitter, critical for mood regulation and executive function, is estimated to be produced up to 90-95% within the gut by the microbiome?",
            "options": [
                "Dopamine",
                "GABA",
                "Serotonin",
                "Glutamate"
            ],
            "correctAnswer": 2,
            "explanation": "While serotonin is used in the brain, the vast majority (90-95%) is synthesized by enterochromaffin cells in the gut, influenced by the microbiome."
        },
        {
            "id": "q8_6",
            "question": "To maintain optimal hydration and prevent performance decline, young athletes should aim to replace fluid lost during exercise at what rate?",
            "options": [
                "4-6 oz of water per pound of weight lost",
                "8-10 oz of water per pound of weight lost",
                "16-24 oz of fluid per pound of weight lost",
                "32-40 oz of fluid per pound of weight lost"
            ],
            "correctAnswer": 2,
            "explanation": "Sports nutrition guidelines recommend 16-24 ounces of fluid for every pound of body weight lost during exercise to ensure full rehydration."
        },
        {
            "id": "q8_7",
            "question": "The landmark LEAP (Learning Early About Peanut Allergy) study demonstrated that early introduction of peanuts in high-risk infants reduced the risk of developing an allergy by approximately what percentage?",
            "options": [
                "25%",
                "50%",
                "81%",
                "99%"
            ],
            "correctAnswer": 2,
            "explanation": "The LEAP study showed a significant 81% reduction in the development of peanut allergies in high-risk infants when peanuts were introduced between 4-11 months of age."
        },
        {
            "id": "q8_8",
            "question": "In the G.R.O.W. Method™ used by AccrediPro coaches, what does the 'O' primarily focus on during a client session?",
            "options": [
                "Ordering laboratory tests",
                "Optimizing macronutrient ratios",
                "Obstacles and Options",
                "Overcoming parental resistance"
            ],
            "correctAnswer": 2,
            "explanation": "The 'O' in the G.R.O.W. Method™ stands for Obstacles and Options, where the coach helps the client identify barriers and brainstorm potential solutions."
        },
        {
            "id": "q8_9",
            "question": "A 10-year-old male athlete presents with a Mid-Parental Height (MPH) calculation. If his father is 72 inches and his mother is 64 inches, what is his target height (using the Khamis-Roche adjusted formula method)?",
            "options": [
                "68 inches",
                "65.5 inches",
                "70.5 inches",
                "74 inches"
            ],
            "correctAnswer": 2,
            "explanation": "For boys: (Father's Height + Mother's Height + 5 inches) / 2. Calculation: (72 + 64 + 5) / 2 = 141 / 2 = 70.5 inches."
        },
        {
            "id": "q8_10",
            "question": "Which of the following actions falls OUTSIDE the professional scope of practice for a Pediatric Nutrition Coach?",
            "options": [
                "Using Z-scores to monitor growth trends",
                "Providing meal ideas for a child with a confirmed Celiac diagnosis",
                "Ordering and interpreting a diagnostic skin-prick test for allergies",
                "Calculating sweat rate for a high school soccer player"
            ],
            "correctAnswer": 2,
            "explanation": "Coaches do not perform clinical diagnostic tests like skin-prick tests; these must be conducted and interpreted by a licensed medical professional (Allergist/Immunologist)."
        }
    ]
}