{
    "course_name": "Narcissistic Abuse Recovery Coach",
    "certification_title": "Certified Narcissistic Abuse Recovery Coach™",
    "methodology": "The N.A.R.C. Recovery Method™",
    "total_modules": 16,
    "modules": [
        {
            "number": 0,
            "title": "Introduction & Career Vision",
            "lessons": [
                {
                    "number": 1,
                    "title": "Welcome to AccrediPro - Your Path to Narcissistic Abuse Recovery Coach Mastery"
                },
                {
                    "number": 2,
                    "title": "Career Paths & Opportunities (8 specific career paths with income potential)"
                },
                {
                    "number": 3,
                    "title": "The Earnings Breakdown (Part-time, Full-time, Scaled practice numbers)"
                },
                {
                    "number": 4,
                    "title": "Your First 90 Days Roadmap (Foundation → Launch → Growth phases)"
                }
            ],
            "has_quiz": false
        },
        {
            "number": 1,
            "title": "Foundations of Narcissistic Abuse & The N.A.R.C. Method™",
            "lessons": [
                {
                    "number": 1,
                    "title": "Understanding Narcissistic Personality Disorder: Clinical Overview"
                },
                {
                    "number": 2,
                    "title": "Introduction to The N.A.R.C. Recovery Method™ Framework"
                },
                {
                    "number": 3,
                    "title": "The Spectrum of Narcissistic Abuse: Overt vs Covert Patterns"
                },
                {
                    "number": 4,
                    "title": "The Practitioner's Scope of Practice and Ethical Boundaries"
                },
                {
                    "number": 5,
                    "title": "Trauma Psychology 101: How Abuse Rewires the Brain"
                },
                {
                    "number": 6,
                    "title": "The Hierarchy of Recovery: Prioritizing Healing Phases"
                },
                {
                    "number": 7,
                    "title": "The Psychology of Victimization: Why Information Isn't Enough"
                },
                {
                    "number": 8,
                    "title": "Case Study Analysis: The Impact of the N.A.R.C. Approach"
                }
            ],
            "has_quiz": true
        },
        {
            "number": 2,
            "title": "N - Navigate the Reality: Recognizing Abuse Patterns",
            "lessons": [
                {
                    "number": 1,
                    "title": "The Narcissistic Abuse Cycle: Idealization, Devaluation, Discard"
                },
                {
                    "number": 2,
                    "title": "Gaslighting and Reality Distortion Techniques"
                },
                {
                    "number": 3,
                    "title": "Love Bombing: The Seduction Phase Decoded"
                },
                {
                    "number": 4,
                    "title": "Emotional Manipulation Tactics: FOG (Fear, Obligation, Guilt)"
                },
                {
                    "number": 5,
                    "title": "Financial Abuse and Control Mechanisms"
                },
                {
                    "number": 6,
                    "title": "Isolation Strategies: Cutting Off Support Systems"
                },
                {
                    "number": 7,
                    "title": "Flying Monkeys and Triangulation Dynamics"
                },
                {
                    "number": 8,
                    "title": "Clinical Applications: Validating Client Experiences"
                }
            ],
            "has_quiz": true
        },
        {
            "number": 3,
            "title": "N - Navigate the Reality: Assessment & Documentation",
            "lessons": [
                {
                    "number": 1,
                    "title": "Comprehensive Intake Assessment for Abuse Survivors"
                },
                {
                    "number": 2,
                    "title": "The Danger Assessment: Safety Planning Protocols"
                },
                {
                    "number": 3,
                    "title": "Identifying Coercive Control Patterns"
                },
                {
                    "number": 4,
                    "title": "Documentation for Legal and Therapeutic Support"
                },
                {
                    "number": 5,
                    "title": "Recognizing Narcissistic Abuse in Different Relationships"
                },
                {
                    "number": 6,
                    "title": "The Workplace Narcissist: Professional Abuse Dynamics"
                },
                {
                    "number": 7,
                    "title": "Familial Narcissism: Parent-Child Dynamics"
                },
                {
                    "number": 8,
                    "title": "Building Your Assessment Toolkit"
                }
            ],
            "has_quiz": true
        },
        {
            "number": 4,
            "title": "A - Acknowledge the Wounds: Trauma Bond Science",
            "lessons": [
                {
                    "number": 1,
                    "title": "The Neuroscience of Trauma Bonding"
                },
                {
                    "number": 2,
                    "title": "Stockholm Syndrome and Cognitive Dissonance"
                },
                {
                    "number": 3,
                    "title": "Intermittent Reinforcement: The Addiction Pattern"
                },
                {
                    "number": 4,
                    "title": "C-PTSD vs PTSD: Understanding Complex Trauma"
                },
                {
                    "number": 5,
                    "title": "The Biological Impact: Cortisol, Adrenaline, and Burnout"
                },
                {
                    "number": 6,
                    "title": "Emotional Flashbacks and Triggers"
                },
                {
                    "number": 7,
                    "title": "The Inner Critic: Internalized Abuse Voice"
                },
                {
                    "number": 8,
                    "title": "Assessment Tools for Trauma Bond Severity"
                }
            ],
            "has_quiz": true
        },
        {
            "number": 5,
            "title": "A - Acknowledge the Wounds: Processing Emotional Damage",
            "lessons": [
                {
                    "number": 1,
                    "title": "The Stages of Grief in Abuse Recovery"
                },
                {
                    "number": 2,
                    "title": "Shame and Self-Blame: Dismantling the False Narrative"
                },
                {
                    "number": 3,
                    "title": "Anger as a Healing Force: Healthy Expression"
                },
                {
                    "number": 4,
                    "title": "Trust Issues and Hypervigilance"
                },
                {
                    "number": 5,
                    "title": "The Fog of Codependency"
                },
                {
                    "number": 6,
                    "title": "Identifying Core Wounds and Unmet Needs"
                },
                {
                    "number": 7,
                    "title": "Inner Child Work for Abuse Survivors"
                },
                {
                    "number": 8,
                    "title": "Somatic Approaches to Trauma Release"
                }
            ],
            "has_quiz": true
        },
        {
            "number": 6,
            "title": "R - Rebuild Identity: Rediscovering Self",
            "lessons": [
                {
                    "number": 1,
                    "title": "The Erosion of Self: How Narcissistic Abuse Dismantles Identity"
                },
                {
                    "number": 2,
                    "title": "Values Clarification and Personal Authenticity"
                },
                {
                    "number": 3,
                    "title": "Reconnecting with Core Interests and Passions"
                },
                {
                    "number": 4,
                    "title": "Self-Compassion Practices for Survivors"
                },
                {
                    "number": 5,
                    "title": "Journaling and Reflective Exercises"
                },
                {
                    "number": 6,
                    "title": "Building Self-Trust After Betrayal"
                },
                {
                    "number": 7,
                    "title": "The Role of Creativity in Identity Rebuilding"
                },
                {
                    "number": 8,
                    "title": "Creating a Personal Mission Statement"
                }
            ],
            "has_quiz": true
        },
        {
            "number": 7,
            "title": "R - Rebuild Identity: Establishing Boundaries",
            "lessons": [
                {
                    "number": 1,
                    "title": "Boundary Fundamentals: What They Are and Why They Matter"
                },
                {
                    "number": 2,
                    "title": "Types of Boundaries: Physical, Emotional, Digital"
                },
                {
                    "number": 3,
                    "title": "The No-Contact Protocol: Implementation Guide"
                },
                {
                    "number": 4,
                    "title": "Gray Rock Technique for Required Contact"
                },
                {
                    "number": 5,
                    "title": "Communicating Boundaries Effectively"
                },
                {
                    "number": 6,
                    "title": "Dealing with Boundary Violations"
                },
                {
                    "number": 7,
                    "title": "Boundaries with Flying Monkeys and Enablers"
                },
                {
                    "number": 8,
                    "title": "Self-Care as Boundary Practice"
                }
            ],
            "has_quiz": true
        },
        {
            "number": 8,
            "title": "C - Claim Your Power: Building Resilience",
            "lessons": [
                {
                    "number": 1,
                    "title": "Post-Traumatic Growth: From Survivor to Thriver"
                },
                {
                    "number": 2,
                    "title": "Cognitive Restructuring Techniques"
                },
                {
                    "number": 3,
                    "title": "Mindfulness and Grounding Practices"
                },
                {
                    "number": 4,
                    "title": "Building a Support Network"
                },
                {
                    "number": 5,
                    "title": "Physical Health and Nervous System Regulation"
                },
                {
                    "number": 6,
                    "title": "Sleep Restoration After Trauma"
                },
                {
                    "number": 7,
                    "title": "Developing Emotional Intelligence"
                },
                {
                    "number": 8,
                    "title": "The Power of Routine and Stability"
                }
            ],
            "has_quiz": true
        },
        {
            "number": 9,
            "title": "C - Claim Your Power: Future Relationships",
            "lessons": [
                {
                    "number": 1,
                    "title": "Red Flag Recognition in New Relationships"
                },
                {
                    "number": 2,
                    "title": "Green Flags: What Healthy Love Looks Like"
                },
                {
                    "number": 3,
                    "title": "Dating After Narcissistic Abuse"
                },
                {
                    "number": 4,
                    "title": "Trust Building in New Connections"
                },
                {
                    "number": 5,
                    "title": "Communicating Your History Appropriately"
                },
                {
                    "number": 6,
                    "title": "Parent-Child Relationship Healing"
                },
                {
                    "number": 7,
                    "title": "Professional and Friendship Boundaries"
                },
                {
                    "number": 8,
                    "title": "Creating Relationship Contracts"
                }
            ],
            "has_quiz": true
        },
        {
            "number": 10,
            "title": "Advanced Coaching Techniques",
            "lessons": [
                {
                    "number": 1,
                    "title": "Motivational Interviewing for Trauma Survivors"
                },
                {
                    "number": 2,
                    "title": "Solution-Focused Brief Coaching Methods"
                },
                {
                    "number": 3,
                    "title": "Cognitive Behavioral Coaching Integration"
                },
                {
                    "number": 4,
                    "title": "Psychoeducation Delivery Skills"
                },
                {
                    "number": 5,
                    "title": "Managing Resistance and Ambivalence"
                },
                {
                    "number": 6,
                    "title": "Crisis Intervention and Safety Protocols"
                },
                {
                    "number": 7,
                    "title": "Working with High-Risk Clients"
                },
                {
                    "number": 8,
                    "title": "Cultural Competency in Abuse Recovery"
                }
            ],
            "has_quiz": true
        },
        {
            "number": 11,
            "title": "Specialized Populations & Situations",
            "lessons": [
                {
                    "number": 1,
                    "title": "Male Victims of Narcissistic Abuse"
                },
                {
                    "number": 2,
                    "title": "LGBTQ+ Relationships and Unique Dynamics"
                },
                {
                    "number": 3,
                    "title": "Children of Narcissistic Parents (Adult Children)"
                },
                {
                    "number": 4,
                    "title": "Co-Parenting with a Narcissist"
                },
                {
                    "number": 5,
                    "title": "Religious and Spiritual Abuse"
                },
                {
                    "number": 6,
                    "title": "Narcissistic Abuse in the Workplace"
                },
                {
                    "number": 7,
                    "title": "Elder Abuse and Late-Life Recovery"
                },
                {
                    "number": 8,
                    "title": "Supporting Loved Ones of Survivors"
                }
            ],
            "has_quiz": true
        },
        {
            "number": 12,
            "title": "Legal & Safety Considerations",
            "lessons": [
                {
                    "number": 1,
                    "title": "Understanding Restraining Orders and Protective Measures"
                },
                {
                    "number": 2,
                    "title": "Documentation for Court Proceedings"
                },
                {
                    "number": 3,
                    "title": "Working with Attorneys and Legal Advocates"
                },
                {
                    "number": 4,
                    "title": "Stalking and Post-Separation Abuse"
                },
                {
                    "number": 5,
                    "title": "Digital Safety and Privacy Protocols"
                },
                {
                    "number": 6,
                    "title": "Financial Recovery and Independence"
                },
                {
                    "number": 7,
                    "title": "Custody Battles and Parental Alienation"
                },
                {
                    "number": 8,
                    "title": "Mandatory Reporting and Ethical Obligations"
                }
            ],
            "has_quiz": true
        },
        {
            "number": 13,
            "title": "Self-Care & Preventing Vicarious Trauma",
            "lessons": [
                {
                    "number": 1,
                    "title": "Understanding Secondary Traumatic Stress"
                },
                {
                    "number": 2,
                    "title": "Compassion Fatigue Prevention Strategies"
                },
                {
                    "number": 3,
                    "title": "Personal Boundaries as a Coach"
                },
                {
                    "number": 4,
                    "title": "Supervision and Peer Support Networks"
                },
                {
                    "number": 5,
                    "title": "Mindfulness and Meditation for Practitioners"
                },
                {
                    "number": 6,
                    "title": "Physical Wellness for Emotional Workers"
                },
                {
                    "number": 7,
                    "title": "Creating Work-Life Balance"
                },
                {
                    "number": 8,
                    "title": "Long-Term Career Sustainability"
                }
            ],
            "has_quiz": true
        },
        {
            "number": 14,
            "title": "Practice Building & Business Mastery",
            "lessons": [
                {
                    "number": 1,
                    "title": "Defining Your Niche and Ideal Client Avatar"
                },
                {
                    "number": 2,
                    "title": "Pricing for Profit: Packaging Your Services for Value"
                },
                {
                    "number": 3,
                    "title": "Digital Marketing Foundations for Recovery Coaches"
                },
                {
                    "number": 4,
                    "title": "Legal Requirements, Insurance, and Documentation"
                },
                {
                    "number": 5,
                    "title": "The Discovery Call: Converting Leads into Clients"
                },
                {
                    "number": 6,
                    "title": "Client Onboarding and Retention Systems"
                },
                {
                    "number": 7,
                    "title": "Scaling Your Practice: Group Programs and Passive Income"
                },
                {
                    "number": 8,
                    "title": "Financial Management and Sustainable Growth"
                }
            ],
            "has_quiz": true
        },
        {
            "number": 15,
            "title": "Your Practitioner Journey",
            "lessons": [
                {
                    "number": 1,
                    "title": "Reflecting on Your Transformation Journey"
                },
                {
                    "number": 2,
                    "title": "Building Your Practice Blueprint"
                },
                {
                    "number": 3,
                    "title": "Your First 30 Days as a Certified Coach"
                },
                {
                    "number": 4,
                    "title": "Pricing & Packaging Your Services for Maximum Value"
                },
                {
                    "number": 5,
                    "title": "Finding Your First Clients - Proven Strategies"
                },
                {
                    "number": 6,
                    "title": "Done-For-You Accelerator Resources (templates, scripts, materials)"
                },
                {
                    "number": 7,
                    "title": "Preparing for Your Certification Exam"
                },
                {
                    "number": 8,
                    "title": "Congratulations & Your Next Steps"
                }
            ],
            "has_quiz": true
        }
    ]
}