{
    "moduleId": "module_06",
    "moduleTitle": "Network & Boundary Architecture (ASCEND Step 5)",
    "passingScore": 80,
    "questions": [
        {
            "id": "q6_1",
            "question": "The Framingham Heart Study research on 'social contagion' suggests that if a person in your direct network (1st degree) becomes happy, your own likelihood of happiness increases by approximately 15%. How far does this effect typically extend?",
            "options": [
                "Only to 1st-degree connections",
                "Up to 3 degrees of separation",
                "Up to 5 degrees of separation",
                "Across the entire local community regardless of connection"
            ],
            "correctAnswer": 1,
            "explanation": "Research by Christakis and Fowler (2008) demonstrated that emotional states like happiness and stress spread through social networks up to three degrees of separation."
        },
        {
            "id": "q6_2",
            "question": "In the context of 'Boundary Architecture,' what is the primary distinction between an 'Internal' and 'External' boundary?",
            "options": [
                "Internal boundaries are for family; external are for work",
                "Internal boundaries regulate self-discipline; external boundaries regulate interactions with others",
                "Internal boundaries are physical; external boundaries are emotional",
                "There is no distinction; they are used interchangeably in coaching"
            ],
            "correctAnswer": 1,
            "explanation": "Internal boundaries involve the self-regulation of your own thoughts and behaviors (e.g., not checking email after 8 PM), while external boundaries involve communicating limits to others."
        },
        {
            "id": "q6_3",
            "question": "When performing a Social Network Audit, which category of 'Social Capital' refers to the diverse connections that provide access to new information, different perspectives, and external resources?",
            "options": [
                "Bonding Social Capital",
                "Bridging Social Capital",
                "Linking Social Capital",
                "Transactional Social Capital"
            ],
            "correctAnswer": 1,
            "explanation": "Bridging Social Capital connects individuals across different social groups, providing 'the strength of weak ties' which is essential for innovation and career growth."
        },
        {
            "id": "q6_4",
            "question": "According to Marshall Rosenberg’s Non-Violent Communication (NVC) framework, which of the following is the correct four-step sequence for conflict resolution?",
            "options": [
                "Judgement, Feeling, Demand, Action",
                "Observation, Emotion, Rationalization, Solution",
                "Observation, Feeling, Need, Request",
                "Criticism, Feeling, Need, Ultimatum"
            ],
            "correctAnswer": 2,
            "explanation": "NVC follows the sequence: 1. Observation (facts without judgment), 2. Feeling (emotions), 3. Need (the underlying value), and 4. Request (specific, actionable ask)."
        },
        {
            "id": "q6_5",
            "question": "The '70% Rule' in delegation is a strategy used to reduce cognitive load. What does this rule specifically advise a leader or client to do?",
            "options": [
                "Only work at 70% capacity to avoid burnout",
                "Delegate a task if the person can perform it at least 70% as well as you can",
                "Outsource 70% of all personal chores to virtual assistants",
                "Expect only a 70% success rate when trying new boundary-setting techniques"
            ],
            "correctAnswer": 1,
            "explanation": "The 70% Rule suggests that if a team member can do a task 70% as well as you, it should be delegated to free up your cognitive bandwidth for high-level strategy."
        },
        {
            "id": "q6_6",
            "question": "Research from the University of Texas found that the mere presence of a smartphone on a desk—even if turned off—reduces 'available cognitive capacity.' This phenomenon is known as:",
            "options": [
                "The Zeigarnik Effect",
                "Digital Amnesia",
                "The Brain Drain Effect",
                "Notification Fatigue"
            ],
            "correctAnswer": 2,
            "explanation": "The 'Brain Drain' effect refers to the cognitive costs of simply resisting the urge to check a device, which occupies 'limited-capacity' cognitive resources."
        },
        {
            "id": "q6_7",
            "question": "In a professional ecosystem, how does a 'Sponsor' differ from a 'Mentor'?",
            "options": [
                "A mentor is paid; a sponsor is a volunteer",
                "A mentor provides advice; a sponsor uses their influence to advocate for your advancement",
                "A sponsor is always a direct supervisor; a mentor is always an external peer",
                "There is no difference; they are synonymous in professional networking"
            ],
            "correctAnswer": 1,
            "explanation": "Mentors provide guidance and 'know-how,' while sponsors are senior leaders who use their 'political capital' to get their protégé promoted or assigned to high-visibility projects."
        },
        {
            "id": "q6_8",
            "question": "Case Study: Mark is a CEO who feels exhausted by 'Decision Fatigue.' He realizes he spends 4 hours a week managing his calendar and travel. Which ASCEND Step 5 intervention is most appropriate?",
            "options": [
                "Practicing mindfulness during travel",
                "The 'Strategic No' to all new invitations",
                "Delegating/Outsourcing to a Virtual Assistant (VA)",
                "Increasing his intake of Vitamin B12"
            ],
            "correctAnswer": 2,
            "explanation": "Low-value, high-frequency administrative tasks are prime candidates for delegation or outsourcing to reduce the cognitive load of decision-making."
        },
        {
            "id": "q6_9",
            "question": "A 2022 study on 'Work-Life Integration' found that 'Segmentors' (those with firm boundaries between work and home) experienced significantly lower levels of burnout than 'Integrators.' What is a common 'Segmentor' strategy?",
            "options": [
                "Checking email at the dinner table to get it over with",
                "Using separate devices for work and personal use",
                "Working from bed to feel more comfortable",
                "Answering client calls during family vacations"
            ],
            "correctAnswer": 1,
            "explanation": "Segmentors use physical and digital tools (like separate phones or distinct workspaces) to create 'environmental cues' that separate their professional and personal lives."
        },
        {
            "id": "q6_10",
            "question": "What is the primary goal of creating a 'Resilience Community' or mutual aid group within a high-stress organization?",
            "options": [
                "To provide a space for complaining about management",
                "To replace the need for professional mental health services",
                "To build 'Social Capital' that buffers against the physiological effects of cortisol",
                "To increase the speed of project delivery through group pressure"
            ],
            "correctAnswer": 2,
            "explanation": "Social support triggers the release of oxytocin, which acts as a natural buffer against cortisol (the stress hormone), enhancing collective resilience."
        }
    ]
}