{
  "acronym": "RESET",
  "full_name": "The R.E.S.E.T. Framework\u2122",
  "letters": [
    {
      "letter": "R",
      "meaning": "Recognize & Reframe",
      "description": "Identify the core issue and reframe negative thought patterns."
    },
    {
      "letter": "E",
      "meaning": "Establish Emotional Connection",
      "description": "Connect with the client's emotional experience of the issue."
    },
    {
      "letter": "S",
      "meaning": "Sequence Tapping Points",
      "description": "Apply EFT tapping sequence on key meridian points while focusing on the issue."
    },
    {
      "letter": "E",
      "meaning": "Evaluate & Ease Intensity",
      "description": "Assess the emotional intensity and continue tapping until reduced."
    },
    {
      "letter": "T",
      "meaning": "Transform & Test Beliefs",
      "description": "Integrate positive beliefs and test their validity to solidify transformation."
    }
  ]
}