{
  "acronym": "NEURON",
  "full_name": "The N.E.U.R.O.N. Framework\u2122",
  "letters": [
    {
      "letter": "N",
      "meaning": "Neuro-Mapping",
      "description": "Assess the client's current cognitive baselines, neurological stressors, and executive function strengths."
    },
    {
      "letter": "E",
      "meaning": "Emotional Regulation",
      "description": "Stabilize the autonomic nervous system to reduce limbic interference and enhance prefrontal cortex engagement."
    },
    {
      "letter": "U",
      "meaning": "Unlocking Plasticity",
      "description": "Apply neuro-priming techniques to increase brain-derived neurotrophic factor (BDNF) and prepare for structural change."
    },
    {
      "letter": "R",
      "meaning": "Rewiring Protocols",
      "description": "Execute targeted cognitive and sensory drills to stimulate specific neural pathways and increase synaptic density."
    },
    {
      "letter": "O",
      "meaning": "Optimizing Bio-Chemistry",
      "description": "Align lifestyle factors like nutrition and sleep to support healthy neurotransmitter production and brain metabolism."
    },
    {
      "letter": "N",
      "meaning": "Neural Consolidation",
      "description": "Solidify newly formed connections through repetitive behavioral loops to ensure long-term habit automaticity."
    }
  ]
}